{"Canada": "rock", "Lithuania": "alternative rock", "Argentina": "rock", "Bolivia": "soundtrack", "Cameroon": "breakbeat", "Ghana": "r&b", "Slovenia": "electronic", "Bosnia and Herzegovina": "political", "Russian Federation": "rock", "Spain": "spanish", "Netherlands": "rock", "Jamaica": "reggae", "Palestinian Territory": "pop", "French Guiana": "retro", "New Zealand": "rock", "Yemen": "sexy", "Pakistan": "world reggae", "India": "electronic", "Turkey": "rock", "Afghanistan": "hard house", "Czech Republic": "rock", "France": "french", "Bermuda": "alternative", "Slovakia": "00s", "Peru": "rock", "Norway": "rock", "Cote d'Ivoire": "european", "Benin": "classic", "Cuba": "latin", "Iran, Islamic Republic of": "pop", "Togo": "rock", "China": "garage rock", "Dominican Republic": "latin", "Ukraine": "alternative", "Indonesia": "rock", "Finland": "rock", "United States": "rock", "Sweden": "rock", "Mali": "alternative", "Bulgaria": "jazz", "Romania": "electronic", "Portugal": "rock", "South Africa": "pop", "Malaysia": "r&b", "Austria": "rock", "Korea, Republic of": "rock", "Hungary": "smooth jazz", "Niger": "techno", "Brazil": "rock", "Panama": "jazz", "Guyana": "club dance", "Costa Rica": "world reggae", "Ireland": "rock", "Nigeria": "soul", "Bangladesh": "electronic", "Australia": "rock", "Algeria": "trip hop", "Chile": "rock", "Puerto Rico": "latin", "Belgium": "rock", "Hong Kong": "pop", "Denmark": "rock", "Philippines": "ost", "Morocco": "country", "Namibia": "hard house", "Switzerland": "electronic", "Isle of Man": "alternative rock", "Tanzania, United Republic of": "alternative rock", "Estonia": "electronic", "Uruguay": "indie", "Lebanon": "acoustic", "Uzbekistan": "jazz rock", "Tunisia": "pop", "Colombia": "rock", "Reunion": "00s", "Burundi": "pop rap", "Taiwan": "hardcore", "Barbados": "techno", "Italy": "rock", "Malta": "00s", "Venezuela": "pop", "Israel": "rock", "Iceland": "rock", "Senegal": "alternative rock", "Germany": "rock", "Martinique": "rock", "Poland": "rock", "Congo, The Democratic Republic of the": "african", "Trinidad and Tobago": "pop", "Latvia": "00s", "Japan": "rock", "Guadeloupe": "dj", "Mexico": "rock", "Egypt": "house", "Singapore": "pop", "Serbia": "rock", "United Kingdom": "rock", "Congo": "pop rap", "Greece": "rock", "Croatia": "electronic"}